README.md
src/xwlazy_wrapper.py
xwlazy-0.1.0.23.dist-info/METADATA
xwlazy-0.1.0.23.dist-info/WHEEL
xwlazy-0.1.0.23.dist-info/licenses/LICENSE
xwlazy-0.1.0.23.dist-info/RECORD
