Metadata-Version: 2.4
Name: xwlazy
Version: 0.1.0.23
Summary: Convenience wrapper for exonware-xwlazy - provides 'import xwlazy' alias
Project-URL: Homepage, https://exonware.com
Project-URL: Repository, https://github.com/exonware/xwlazy
Project-URL: Documentation, https://github.com/exonware/xwlazy#readme
Project-URL: Subtree, https://github.com/Exonware/XWLazy.git
Author-email: "Eng. Muhammad AlShehri" <connect@exonware.com>
License: MIT
License-File: LICENSE
Keywords: exonware,lazy,xwlazy
Classifier: Development Status :: 4 - Beta
Classifier: Intended Audience :: Developers
Classifier: License :: OSI Approved :: MIT License
Classifier: Operating System :: OS Independent
Classifier: Programming Language :: Python :: 3
Classifier: Programming Language :: Python :: 3.12
Classifier: Topic :: Software Development :: Libraries :: Python Modules
Requires-Python: >=3.12
Requires-Dist: exonware-xwlazy
